intuginehelper/__init__.py
intuginehelper/intudb.py
intuginehelper/intuhelper.py
intuginehelper/intuparser.py
IntugineHelper-1.2.dist-info/METADATA
IntugineHelper-1.2.dist-info/WHEEL
IntugineHelper-1.2.dist-info/top_level.txt
IntugineHelper-1.2.dist-info/RECORD
