Metadata-Version: 2.1
Name: IntugineHelper
Version: 1.2
Summary: A Helper for Intugine
Home-page: https://github.com/rishabhdeepsingh/IntugineHelper
Author: Rishabhdeep Singh
Author-email: rishabhdeepsingh98@gmail.com
License: UNKNOWN
Platform: UNKNOWN
Classifier: Programming Language :: Python :: 3
Classifier: License :: OSI Approved :: MIT License
Classifier: Operating System :: OS Independent
Requires-Dist: pymongo
Requires-Dist: dnspython
Requires-Dist: datetime
